{
   "layout":{
      "pages":[
         {
            "id":"page_1",
            "title":"EfficientIP SOLIDserver IPAM endpoint",
            "sections":[
               {
                  "id":"secion_1",
                  "fields":[
                     {
                        "id":"privateKeyId",
                        "display":"textField"
                     },
                     {
                        "id":"privateKey",
                        "display":"passwordField"
                     },
                     {
                        "id":"hostName",
                        "display":"textField"
                     },
                     {
                        "id":"properties",
                        "display":"datagrid"
                     }
                  ]
               }
            ]
         }
      ]
   },
   "schema":{
      "privateKeyId":{
         "type":{
            "dataType":"string"
         },
         "label":"Username",
         "placeholder": "automation",
         "constraints":{
            "required":true
         }
      },
      "privateKey":{
         "type":{
            "dataType":"secureString"
         },
         "label":"Password",
         "constraints":{
            "required":true
         }
      },
      "hostName":{
         "type":{
            "dataType":"string"
         },
         "label":"Hostname",
         "placeholder": "ns0.example.com",
         "constraints":{
            "required":true
         }
      },
      "properties":{
         "label":"Properties",
         "type":{
            "dataType":"complex",
            "isMultiple":true,
            "fields":[
               {
                  "label":"Key",
                  "id":"prop_key",
                  "type":{
                     "dataType":"string"
                  }
               },
               {
                  "label":"Value",
                  "id":"prop_value",
                  "type":{
                     "dataType":"string"
                  }
               }
            ]
         },
         "default":[
            {  
               "prop_key":"dnsServerAddresses",
               "prop_value":"1.1.1.1, 1.0.0.1"
            },
            {  
               "prop_key":"use_pool",
               "prop_value":"True"
            },
            {  
               "prop_key":"pool_site_name",
               "prop_value":""
            },
            {  
               "prop_key":"use_subnet",
               "prop_value":"False"
            },
            {  
               "prop_key":"subnet_site_name",
               "prop_value":""
            }
         ]
      }
   },
   "options":{

   }
}
